ipypolaroid/__init__.py
ipypolaroid/_frontend.py
ipypolaroid/_version.py
ipypolaroid/widget.py
ipypolaroid/labextension/build_log.json
ipypolaroid/labextension/package.json
ipypolaroid/labextension/static/lib_index_js.29cded063b9083fd5c06.js
ipypolaroid/labextension/static/lib_index_js.29cded063b9083fd5c06.js.map
ipypolaroid/labextension/static/lib_index_js.905357f5cbdc93d6c875.js
ipypolaroid/labextension/static/lib_index_js.905357f5cbdc93d6c875.js.map
ipypolaroid/labextension/static/lib_plugin_js.99366b761c58b8b0ccf1.js
ipypolaroid/labextension/static/lib_plugin_js.99366b761c58b8b0ccf1.js.map
ipypolaroid/labextension/static/lib_widget_js.015b0509ffdace62956e.js
ipypolaroid/labextension/static/lib_widget_js.015b0509ffdace62956e.js.map
ipypolaroid/labextension/static/lib_widget_js.0233f6f03c3aa2055ddc.js
ipypolaroid/labextension/static/lib_widget_js.0233f6f03c3aa2055ddc.js.map
ipypolaroid/labextension/static/lib_widget_js.07bf180326b80cd3280a.js
ipypolaroid/labextension/static/lib_widget_js.07bf180326b80cd3280a.js.map
ipypolaroid/labextension/static/lib_widget_js.0fb733f04a5e69450d40.js
ipypolaroid/labextension/static/lib_widget_js.0fb733f04a5e69450d40.js.map
ipypolaroid/labextension/static/lib_widget_js.0fcb4572781bb9a2ac07.js
ipypolaroid/labextension/static/lib_widget_js.0fcb4572781bb9a2ac07.js.map
ipypolaroid/labextension/static/lib_widget_js.11bb80904ed31847c5b2.js
ipypolaroid/labextension/static/lib_widget_js.11bb80904ed31847c5b2.js.map
ipypolaroid/labextension/static/lib_widget_js.1354bf7b713bc2ce7620.js
ipypolaroid/labextension/static/lib_widget_js.1354bf7b713bc2ce7620.js.map
ipypolaroid/labextension/static/lib_widget_js.1dac1d2848fa29c49884.js
ipypolaroid/labextension/static/lib_widget_js.1dac1d2848fa29c49884.js.map
ipypolaroid/labextension/static/lib_widget_js.30d246bc407a1ed8e424.js
ipypolaroid/labextension/static/lib_widget_js.30d246bc407a1ed8e424.js.map
ipypolaroid/labextension/static/lib_widget_js.31df6117cb658399eda3.js
ipypolaroid-0.1.1.dev0.dist-info/LICENSE.txt
ipypolaroid-0.1.1.dev0.dist-info/METADATA
ipypolaroid-0.1.1.dev0.dist-info/WHEEL
ipypolaroid-0.1.1.dev0.dist-info/top_level.txt
ipypolaroid-0.1.1.dev0.dist-info/RECORD
